bowler/__init__.py
bowler/__main__.py
bowler/helpers.py
bowler/imr.py
bowler/main.py
bowler/query.py
bowler/tool.py
bowler/type_inference.py
bowler/types.py
bowler/tests/__init__.py
bowler/tests/__main__.py
bowler/tests/helpers.py
bowler/tests/lib.py
bowler/tests/query.py
bowler/tests/smoke-target.py
bowler/tests/smoke.py
bowler/tests/tool.py
bowler/tests/type_inference.py
bowler-0.8.0.dist-info/LICENSE
bowler-0.8.0.dist-info/METADATA
bowler-0.8.0.dist-info/WHEEL
bowler-0.8.0.dist-info/entry_points.txt
bowler-0.8.0.dist-info/top_level.txt
bowler-0.8.0.dist-info/RECORD
