Metadata-Version: 2.1
Name: bowler
Version: 0.8.0
Summary: Safe code refactoring for modern Python projects
Home-page: https://github.com/facebookincubator/bowler
Author: John Reese, Facebook
Author-email: jreese@fb.com
License: MIT
Platform: UNKNOWN
Classifier: Development Status :: 1 - Planning
Classifier: Intended Audience :: Developers
Classifier: License :: OSI Approved :: MIT License
Classifier: Programming Language :: Python
Classifier: Programming Language :: Python :: 3
Classifier: Programming Language :: Python :: 3.6
Classifier: Programming Language :: Python :: 3.7
Requires-Python: >=3.6
Requires-Dist: attrs
Requires-Dist: click
Requires-Dist: fissix
Requires-Dist: sh
